smcphub_client/__init__.py
smcphub_client/client.py
smcphub_client-0.0.3.dist-info/licenses/LICENSE
smcphub_client-0.0.3.dist-info/METADATA
smcphub_client-0.0.3.dist-info/WHEEL
smcphub_client-0.0.3.dist-info/top_level.txt
smcphub_client-0.0.3.dist-info/RECORD
