Metadata-Version: 2.4
Name: smcphub-client
Version: 0.0.3
Summary: A MCP client of SMCPHUB
Author-email: SMCPHUB <smcphub@163.com>
License: MIT
Project-URL: Homepage, https://smcphub.com
Keywords: mcp,mcp client,smcphub,llm,automation
Classifier: Programming Language :: Python :: 3
Classifier: Programming Language :: Python :: 3.10
Classifier: License :: OSI Approved :: MIT License
Classifier: Operating System :: OS Independent
Classifier: Development Status :: 4 - Beta
Classifier: Intended Audience :: Developers
Classifier: Topic :: Software Development :: Libraries :: Python Modules
Requires-Python: >=3.10
License-File: LICENSE
Requires-Dist: mcp>=1.6.0
Dynamic: license-file
